business_brio_package/__init__.py
business_brio_package/percentile_significance.py
business_brio_package/performance_rank_discrete.py
business_brio_package-0.0.6.dist-info/LICENSE
business_brio_package-0.0.6.dist-info/METADATA
business_brio_package-0.0.6.dist-info/WHEEL
business_brio_package-0.0.6.dist-info/top_level.txt
business_brio_package-0.0.6.dist-info/RECORD
